img2vec_pytorch/__init__.py
img2vec_pytorch/img_to_vec.py
img2vec_pytorch/test_img_to_vec.py
img2vec_pytorch-1.0.2.dist-info/licenses/LICENSE.txt
img2vec_pytorch-1.0.2.dist-info/METADATA
img2vec_pytorch-1.0.2.dist-info/WHEEL
img2vec_pytorch-1.0.2.dist-info/top_level.txt
img2vec_pytorch-1.0.2.dist-info/RECORD
