Metadata-Version: 2.4
Name: img2vec_pytorch
Version: 1.0.2
Summary: Use pre-trained models in PyTorch to extract vector embeddings for any image
Home-page: https://github.com/christiansafka/img2vec
Author: Christian Safka
Author-email: christiansafka@gmail.com
License: MIT
Keywords: img2vec image vector classification pytorch convert
Classifier: License :: OSI Approved :: MIT License
Classifier: Programming Language :: Python :: 3.6
Requires-Python: >=3.6
License-File: LICENSE.txt
Requires-Dist: torch
Requires-Dist: torchvision
Requires-Dist: numpy
Dynamic: author
Dynamic: author-email
Dynamic: classifier
Dynamic: description
Dynamic: description-content-type
Dynamic: home-page
Dynamic: keywords
Dynamic: license
Dynamic: license-file
Dynamic: requires-dist
Dynamic: requires-python
Dynamic: summary
